huaweicloudsdkgaussdbforopengauss/__init__.py
huaweicloudsdkgaussdbforopengauss/v3/__init__.py
huaweicloudsdkgaussdbforopengauss/v3/gaussdbforopengauss_async_client.py
huaweicloudsdkgaussdbforopengauss/v3/gaussdbforopengauss_client.py
huaweicloudsdkgaussdbforopengauss/v3/model/__init__.py
huaweicloudsdkgaussdbforopengauss/v3/model/add_hba_conf_request_body.py
huaweicloudsdkgaussdbforopengauss/v3/model/add_hba_confs_request.py
huaweicloudsdkgaussdbforopengauss/v3/model/add_hba_confs_response.py
huaweicloudsdkgaussdbforopengauss/v3/model/add_instance_tags_request.py
huaweicloudsdkgaussdbforopengauss/v3/model/add_instance_tags_response.py
huaweicloudsdkgaussdbforopengauss/v3/model/add_tags_request_body.py
huaweicloudsdkgaussdbforopengauss/v3/model/after_hba_conf_option.py
huaweicloudsdkgaussdbforopengauss/v3/model/agency_role_result.py
huaweicloudsdkgaussdbforopengauss/v3/model/alarm_history_record_result.py
huaweicloudsdkgaussdbforopengauss/v3/model/alarm_level_statistics_result.py
huaweicloudsdkgaussdbforopengauss/v3/model/allow_db_privileges_request.py
huaweicloudsdkgaussdbforopengauss/v3/model/allow_db_privileges_response.py
huaweicloudsdkgaussdbforopengauss/v3/model/allow_db_role_privileges_request.py
huaweicloudsdkgaussdbforopengauss/v3/model/allow_db_role_privileges_request_body.py
huaweicloudsdkgaussdbforopengauss/v3/model/allow_db_role_privileges_response.py
huaweicloudsdkgaussdbforopengauss/v3/model/applied_histories_result.py
huaweicloudsdkgaussdbforopengauss/v3/model/apply_configuration_request_body.py
huaweicloudsdkgaussdbforopengauss/v3/model/attach_eip_request.py
huaweicloudsdkgaussdbforopengauss/v3/model/attach_eip_response.py
huaweicloudsdkgaussdbforopengauss/v3/model/authorize_backup_download_request.py
huaweicloudsdkgaussdbforopengauss/v3/model/authorize_backup_download_response.py
huaweicloudsdkgaussdbforopengauss/v3/model/available_flavor_info_result.py
huaweicloudsdkgaussdbforopengauss/v3/model/backup_info.py
huaweicloudsdkgaussdbforopengauss-3.1.184.dist-info/METADATA
huaweicloudsdkgaussdbforopengauss-3.1.184.dist-info/WHEEL
huaweicloudsdkgaussdbforopengauss-3.1.184.dist-info/licenses/LICENSE
huaweicloudsdkgaussdbforopengauss-3.1.184.dist-info/RECORD
